gerber_renderer/Gerber.py
gerber_renderer/__init__.py
gerber_renderer-0.1.4.dist-info/LICENSE
gerber_renderer-0.1.4.dist-info/METADATA
gerber_renderer-0.1.4.dist-info/WHEEL
gerber_renderer-0.1.4.dist-info/top_level.txt
gerber_renderer-0.1.4.dist-info/RECORD
