Metadata-Version: 2.1
Name: gerber-renderer
Version: 0.1.4
Summary: A library for rendering gerber files as SVGs and PDFs
Home-page: https://github.com/Pitwuk/gerber_renderer
Author: Patrick Ogden
Author-email: plogden2@gmail.com
License: UNKNOWN
Platform: UNKNOWN
Classifier: Programming Language :: Python :: 3
Classifier: License :: OSI Approved :: MIT License
Classifier: Operating System :: OS Independent
Requires-Python: >=3.6
Requires-Dist: svgwrite (>=1.4)
Requires-Dist: reportlab (>=3.5)
Requires-Dist: svglib (>=1.0)
